threadify/__init__.py
threadify/threadify.py
threadify-1.0.0.dist-info/LICENSE.TXT
threadify-1.0.0.dist-info/METADATA
threadify-1.0.0.dist-info/WHEEL
threadify-1.0.0.dist-info/top_level.txt
threadify-1.0.0.dist-info/RECORD
