Metadata-Version: 2.1
Name: threadify
Version: 1.0.0
Summary: An enhancement to Python threads that adds cooperative pause, unpause, and kill capabilities.
Home-page: https://github.com/300bps/threadify
Author: David Smith
Author-email: x300bps@icloud.com
License: MIT
Keywords: thread threading concurrent cooperative multitasking multithreading pause kill
Platform: UNKNOWN
Classifier: Programming Language :: Python :: 3
Classifier: License :: OSI Approved :: MIT License
Classifier: Operating System :: OS Independent
